guvicorn_logger/__init__.py
guvicorn_logger/core.py
guvicorn_logger/logger.py
guvicorn_logger-0.1.17.dist-info/METADATA
guvicorn_logger-0.1.17.dist-info/WHEEL
guvicorn_logger-0.1.17.dist-info/RECORD
