Metadata-Version: 2.1
Name: guvicorn_logger
Version: 0.1.17
Summary: Colored, normalizes and joins logs between Uvicorn and Gunicorn.
Home-page: https://github.com/carlos-rian/guvicorn_logger
License: MIT
Keywords: gunicorn,uvicorn,logs,logging
Author: carlos.rian
Author-email: crian.rian@gmail.com
Requires-Python: >=3.8,<4.0
Classifier: License :: OSI Approved :: MIT License
Classifier: Programming Language :: Python :: 3
Classifier: Programming Language :: Python :: 3.8
Classifier: Programming Language :: Python :: 3.9
Classifier: Programming Language :: Python :: 3.10
Classifier: Programming Language :: Python :: 3.11
Classifier: Programming Language :: Python :: 3.12
Requires-Dist: asgi-correlation-id
Requires-Dist: gunicorn
Requires-Dist: uvicorn
Project-URL: Repository, https://github.com/carlos-rian/guvicorn_logger
